LoggerManager/__init__.py
LoggerManager/loggers/__init__.py
LoggerManager/loggers/base_logger_manager.py
LoggerManager/loggers/console_logger_manager.py
LoggerManager/loggers/file_logger_manager.py
LoggerManager/loggers/logger_manager.py
LoggerManager/utils/__init__.py
LoggerManager/utils/errors.py
LoggerManager/utils/filter.py
LoggerManager/utils/formatter.py
LoggerManager/utils/internal_logger.py
LoggerManager/utils/logger_typing.py
LoggerManager/utils/time_execution.py
LoggerManager-0.1.3.1.dist-info/METADATA
LoggerManager-0.1.3.1.dist-info/WHEEL
LoggerManager-0.1.3.1.dist-info/top_level.txt
LoggerManager-0.1.3.1.dist-info/RECORD
