Metadata-Version: 2.1
Name: LoggerManager
Version: 0.1.3.1
Summary: A module that extends the standard Python logging module.
Home-page: https://vk.com/zloboglaz
Author: Amgarak
Author-email: painkiller_97@mail.ru
License: Apache License 2.0
Keywords: logging logger log management log filtering console logging file logging rotating file handler logger configuration log levels internal logger log formatting python logging log management system logging utilities log rotation custom logging
Classifier: Development Status :: 3 - Alpha
Classifier: Intended Audience :: Developers
Classifier: License :: OSI Approved :: Apache Software License
Classifier: Programming Language :: Python :: 3.10
Classifier: Programming Language :: Python :: 3.11
Classifier: Operating System :: OS Independent
Requires-Python: >=3.10
